{
  "players": [
    {
      "id": "690d4b8c-7c3f-40ef-be54-344b45690ef1",
      "name": "Alex",
      "balance": 1000,
      "createdAt": "2026-05-29T04:11:58.470Z",
      "lastDailyBonus": 0,
      "stats": {
        "gamesPlayed": 0,
        "wagered": 0,
        "won": 0,
        "biggestWin": 0
      },
      "history": [],
      "bj": null,
      "nameKey": "alex",
      "lastRescueBonus": 0
    },
    {
      "id": "dba8207f-7a0c-48d8-8f48-1cbc4ffc183c",
      "name": "ff",
      "balance": 1340,
      "createdAt": "2026-05-29T04:12:05.951Z",
      "lastDailyBonus": 0,
      "stats": {
        "gamesPlayed": 3,
        "wagered": 160,
        "won": 360,
        "biggestWin": 360
      },
      "history": [
        {
          "game": "slots",
          "bet": 120,
          "payout": 480,
          "net": 360,
          "detail": "🍒 🍒 🍒 · triple",
          "at": "2026-05-29T04:14:45.515Z"
        },
        {
          "game": "slots",
          "bet": 20,
          "payout": 0,
          "net": -20,
          "detail": "⭐ 🍋 🔔 · none",
          "at": "2026-05-29T04:14:41.304Z"
        },
        {
          "game": "slots",
          "bet": 20,
          "payout": 20,
          "net": 0,
          "detail": "🍒 🔔 ⭐ · one-cherry",
          "at": "2026-05-29T04:12:09.091Z"
        }
      ],
      "bj": null,
      "nameKey": "ff",
      "lastRescueBonus": 0
    },
    {
      "id": "19e6d18c-965f-459b-b4ba-7cadb7533706",
      "name": "dd",
      "balance": 250,
      "createdAt": "2026-05-29T04:15:01.481Z",
      "lastDailyBonus": 1780028106214,
      "stats": {
        "gamesPlayed": 3,
        "wagered": 2250,
        "won": 250,
        "biggestWin": 250
      },
      "history": [
        {
          "game": "coinflip",
          "bet": 500,
          "payout": 0,
          "net": -500,
          "detail": "heads · landed tails",
          "at": "2026-05-29T04:15:34.814Z"
        },
        {
          "game": "coinflip",
          "bet": 250,
          "payout": 500,
          "net": 250,
          "detail": "heads · landed heads",
          "at": "2026-05-29T04:15:30.346Z"
        },
        {
          "game": "coinflip",
          "bet": 1500,
          "payout": 0,
          "net": -1500,
          "detail": "heads · landed tails",
          "at": "2026-05-29T04:15:19.817Z"
        }
      ],
      "bj": null,
      "nameKey": "dd",
      "lastRescueBonus": 0
    },
    {
      "id": "411ebbd9-6720-49ea-8a69-fc8af751f158",
      "name": "CodexTest",
      "nameKey": "codextest",
      "balance": 1000,
      "createdAt": "2026-05-29T04:16:20.676Z",
      "lastDailyBonus": 0,
      "stats": {
        "gamesPlayed": 0,
        "wagered": 0,
        "won": 0,
        "biggestWin": 0
      },
      "history": [],
      "bj": null,
      "passwordSalt": "c904c1a2f160c0bff75f322d0a136333",
      "passwordHash": "c39d25f707805f983a0bf6b587da7b8ee63dd86f0518094e02fd4691a9ad9ea472f939773e50cb76d0a0b5239a3ca7ce6b0fde263136531a6ebaffebeadde97c",
      "lastRescueBonus": 0
    },
    {
      "id": "4010e0ad-7893-4939-80d9-d142e39b6832",
      "name": "Alexxxx",
      "nameKey": "alexxxx",
      "balance": 150,
      "createdAt": "2026-05-29T04:16:38.784Z",
      "lastDailyBonus": 1780028209807,
      "stats": {
        "gamesPlayed": 6,
        "wagered": 4345,
        "won": 1025,
        "biggestWin": 825
      },
      "history": [
        {
          "game": "coinflip",
          "bet": 100,
          "payout": 0,
          "net": -100,
          "detail": "tails · landed heads",
          "at": "2026-05-29T04:17:47.627Z"
        },
        {
          "game": "wheel",
          "bet": 2475,
          "payout": 0,
          "net": -2475,
          "detail": "0x (0x)",
          "at": "2026-05-29T04:17:30.313Z"
        },
        {
          "game": "wheel",
          "bet": 1650,
          "payout": 2475,
          "net": 825,
          "detail": "1.5x (1.5x)",
          "at": "2026-05-29T04:17:18.755Z"
        },
        {
          "game": "wheel",
          "bet": 50,
          "payout": 250,
          "net": 200,
          "detail": "5x (5x)",
          "at": "2026-05-29T04:17:06.663Z"
        },
        {
          "game": "wheel",
          "bet": 50,
          "payout": 0,
          "net": -50,
          "detail": "0x (0x)",
          "at": "2026-05-29T04:16:56.790Z"
        },
        {
          "game": "slots",
          "bet": 20,
          "payout": 20,
          "net": 0,
          "detail": "🍋 🍒 💎 · one-cherry",
          "at": "2026-05-29T04:16:48.435Z"
        }
      ],
      "bj": null,
      "passwordSalt": "fb66df21f890ed81728ef1b489bffffe",
      "passwordHash": "afc62786bb1b0a855c3245abc9fd9f79457f16a09866d509cc7abed44b904e182d54bb7b141eed1ecc49edf76f044cf1bb827ceaafb088524105f93e533f70f5",
      "lastRescueBonus": 0
    },
    {
      "id": "10076633-0346-46e2-b02d-c350e0f471fa",
      "name": "VerifyPlayer",
      "nameKey": "verifyplayer",
      "balance": 1000,
      "createdAt": "2026-05-29T04:17:27.087Z",
      "lastDailyBonus": 0,
      "stats": {
        "gamesPlayed": 0,
        "wagered": 0,
        "won": 0,
        "biggestWin": 0
      },
      "history": [],
      "bj": null,
      "passwordSalt": "894e6df498ca54ccc3223e2c344c0e8e",
      "passwordHash": "ba319d44ba284664f5e7d713e5fbe7e1d9bcf63dc2f019f5eaed00bad8b0606e6f264da099622fa56fa6fad6d20fb883f24eb6a83d76d6839262e9d6f7d02ede",
      "lastRescueBonus": 0
    },
    {
      "id": "0354498b-c136-420b-956f-2f5fac513dac",
      "name": "Фдуч",
      "nameKey": "фдуч",
      "balance": 945.8,
      "createdAt": "2026-05-29T04:36:16.704Z",
      "lastDailyBonus": 0,
      "stats": {
        "gamesPlayed": 2,
        "wagered": 70,
        "won": 0,
        "biggestWin": 0
      },
      "history": [
        {
          "game": "crash",
          "bet": 50,
          "payout": 0,
          "net": -50,
          "detail": "target 2x · crashed 1.19x",
          "at": "2026-05-29T04:37:25.014Z"
        },
        {
          "game": "slots",
          "bet": 20,
          "payout": 15.8,
          "net": -4.199999999999999,
          "detail": "💎 🍒 🍋 · one-cherry",
          "at": "2026-05-29T04:37:08.446Z"
        }
      ],
      "bj": null,
      "passwordSalt": "f358b005a1ccb6be04cf5f163a04343d",
      "passwordHash": "ebaea35194a8fe0cf07e7cdbee76d8ee0a86510529c80f253e20c8dc766b0ec4ddc63bc92413d118c51c1b14099a0f22255f1e4581f753d3906a14ad9902856b",
      "lastRescueBonus": 0
    },
    {
      "id": "1b80b606-6be2-4504-92ee-4002ba83d27d",
      "name": "Alex 🌴",
      "nameKey": "alex 🌴",
      "telegramId": "5638062250",
      "telegramUsername": "Alex_Kozak",
      "balance": 1715.9999999999998,
      "createdAt": "2026-05-29T04:55:58.436Z",
      "lastDailyBonus": 1780030863131,
      "lastRescueBonus": 0,
      "stats": {
        "gamesPlayed": 32,
        "wagered": 2230,
        "won": 734.6,
        "biggestWin": 221
      },
      "history": [
        {
          "game": "dice",
          "bet": 100,
          "payout": 130,
          "net": 30,
          "detail": "roll 63.05 < 75",
          "at": "2026-05-29T05:49:13.469Z"
        },
        {
          "game": "dice",
          "bet": 100,
          "payout": 0,
          "net": -100,
          "detail": "roll 96.17 < 75",
          "at": "2026-05-29T05:49:12.225Z"
        },
        {
          "game": "dice",
          "bet": 100,
          "payout": 130,
          "net": 30,
          "detail": "roll 14.95 < 75",
          "at": "2026-05-29T05:49:11.062Z"
        },
        {
          "game": "dice",
          "bet": 100,
          "payout": 130,
          "net": 30,
          "detail": "roll 34.46 < 75",
          "at": "2026-05-29T05:49:09.752Z"
        },
        {
          "game": "dice",
          "bet": 100,
          "payout": 0,
          "net": -100,
          "detail": "roll 88.59 < 75",
          "at": "2026-05-29T05:49:08.471Z"
        },
        {
          "game": "dice",
          "bet": 100,
          "payout": 130,
          "net": 30,
          "detail": "roll 3.84 < 75",
          "at": "2026-05-29T05:49:07.200Z"
        },
        {
          "game": "dice",
          "bet": 100,
          "payout": 130,
          "net": 30,
          "detail": "roll 40.08 < 75",
          "at": "2026-05-29T05:49:05.993Z"
        },
        {
          "game": "dice",
          "bet": 100,
          "payout": 0,
          "net": -100,
          "detail": "roll 97.49 < 75",
          "at": "2026-05-29T05:49:04.730Z"
        },
        {
          "game": "dice",
          "bet": 100,
          "payout": 130,
          "net": 30,
          "detail": "roll 49.10 < 75",
          "at": "2026-05-29T05:49:03.528Z"
        },
        {
          "game": "dice",
          "bet": 100,
          "payout": 130,
          "net": 30,
          "detail": "roll 72.78 < 75",
          "at": "2026-05-29T05:49:02.072Z"
        },
        {
          "game": "dice",
          "bet": 100,
          "payout": 130,
          "net": 30,
          "detail": "roll 50.63 < 75",
          "at": "2026-05-29T05:49:00.479Z"
        },
        {
          "game": "dice",
          "bet": 100,
          "payout": 130,
          "net": 30,
          "detail": "roll 25.46 < 75",
          "at": "2026-05-29T05:48:58.156Z"
        },
        {
          "game": "dice",
          "bet": 100,
          "payout": 130,
          "net": 30,
          "detail": "roll 39.92 < 75",
          "at": "2026-05-29T05:48:56.487Z"
        },
        {
          "game": "dice",
          "bet": 100,
          "payout": 130,
          "net": 30,
          "detail": "roll 42.55 < 75",
          "at": "2026-05-29T05:48:54.608Z"
        },
        {
          "game": "dice",
          "bet": 100,
          "payout": 130,
          "net": 30,
          "detail": "roll 31.60 < 75",
          "at": "2026-05-29T05:48:47.715Z"
        },
        {
          "game": "dice",
          "bet": 50,
          "payout": 50,
          "net": 0,
          "detail": "roll 33.63 < 98",
          "at": "2026-05-29T05:48:13.479Z"
        },
        {
          "game": "dice",
          "bet": 50,
          "payout": 50,
          "net": 0,
          "detail": "roll 35.37 < 98",
          "at": "2026-05-29T05:48:10.155Z"
        },
        {
          "game": "dice",
          "bet": 50,
          "payout": 50,
          "net": 0,
          "detail": "roll 20.51 < 98",
          "at": "2026-05-29T05:48:05.738Z"
        },
        {
          "game": "slots",
          "bet": 20,
          "payout": 15.8,
          "net": -4.199999999999999,
          "detail": "🍒 💎 🔔 · one-cherry",
          "at": "2026-05-29T05:47:38.972Z"
        },
        {
          "game": "slots",
          "bet": 20,
          "payout": 0,
          "net": -20,
          "detail": "⭐ 🍋 🔔 · none",
          "at": "2026-05-29T05:47:32.015Z"
        },
        {
          "game": "slots",
          "bet": 20,
          "payout": 0,
          "net": -20,
          "detail": "💎 🍋 ⭐ · none",
          "at": "2026-05-29T05:47:25.263Z"
        },
        {
          "game": "slots",
          "bet": 20,
          "payout": 0,
          "net": -20,
          "detail": "🍋 💎 💎 · none",
          "at": "2026-05-29T05:03:08.879Z"
        },
        {
          "game": "slots",
          "bet": 20,
          "payout": 15.8,
          "net": -4.199999999999999,
          "detail": "🍒 🍋 ⭐ · one-cherry",
          "at": "2026-05-29T05:03:02.456Z"
        },
        {
          "game": "slots",
          "bet": 20,
          "payout": 0,
          "net": -20,
          "detail": "🔔 🔔 7️⃣ · none",
          "at": "2026-05-29T05:02:32.665Z"
        },
        {
          "game": "slots",
          "bet": 20,
          "payout": 15.8,
          "net": -4.199999999999999,
          "detail": "💎 🍒 🍋 · one-cherry",
          "at": "2026-05-29T05:02:25.676Z"
        }
      ],
      "bj": {
        "deck": [
          {
            "r": "Q",
            "s": "♥"
          },
          {
            "r": "J",
            "s": "♠"
          },
          {
            "r": "Q",
            "s": "♦"
          },
          {
            "r": "6",
            "s": "♣"
          },
          {
            "r": "8",
            "s": "♠"
          },
          {
            "r": "5",
            "s": "♣"
          },
          {
            "r": "5",
            "s": "♦"
          },
          {
            "r": "J",
            "s": "♦"
          },
          {
            "r": "7",
            "s": "♥"
          },
          {
            "r": "J",
            "s": "♥"
          },
          {
            "r": "K",
            "s": "♠"
          },
          {
            "r": "K",
            "s": "♦"
          },
          {
            "r": "A",
            "s": "♠"
          },
          {
            "r": "K",
            "s": "♣"
          },
          {
            "r": "Q",
            "s": "♠"
          },
          {
            "r": "10",
            "s": "♣"
          },
          {
            "r": "4",
            "s": "♠"
          },
          {
            "r": "10",
            "s": "♥"
          },
          {
            "r": "10",
            "s": "♦"
          },
          {
            "r": "5",
            "s": "♠"
          },
          {
            "r": "10",
            "s": "♠"
          },
          {
            "r": "9",
            "s": "♠"
          },
          {
            "r": "3",
            "s": "♦"
          },
          {
            "r": "9",
            "s": "♥"
          },
          {
            "r": "A",
            "s": "♦"
          },
          {
            "r": "K",
            "s": "♥"
          },
          {
            "r": "4",
            "s": "♦"
          },
          {
            "r": "2",
            "s": "♣"
          },
          {
            "r": "3",
            "s": "♣"
          },
          {
            "r": "5",
            "s": "♥"
          },
          {
            "r": "2",
            "s": "♥"
          },
          {
            "r": "7",
            "s": "♠"
          },
          {
            "r": "3",
            "s": "♠"
          },
          {
            "r": "9",
            "s": "♣"
          },
          {
            "r": "6",
            "s": "♥"
          },
          {
            "r": "7",
            "s": "♦"
          },
          {
            "r": "8",
            "s": "♦"
          },
          {
            "r": "8",
            "s": "♥"
          },
          {
            "r": "6",
            "s": "♠"
          },
          {
            "r": "8",
            "s": "♣"
          },
          {
            "r": "2",
            "s": "♦"
          },
          {
            "r": "A",
            "s": "♥"
          },
          {
            "r": "A",
            "s": "♣"
          },
          {
            "r": "4",
            "s": "♥"
          },
          {
            "r": "4",
            "s": "♣"
          },
          {
            "r": "J",
            "s": "♣"
          }
        ],
        "playerHand": [
          {
            "r": "Q",
            "s": "♣"
          },
          {
            "r": "2",
            "s": "♠"
          },
          {
            "r": "6",
            "s": "♦"
          }
        ],
        "dealerHand": [
          {
            "r": "3",
            "s": "♥"
          },
          {
            "r": "7",
            "s": "♣"
          },
          {
            "r": "9",
            "s": "♦"
          }
        ],
        "bet": 100,
        "status": "done",
        "doubled": false,
        "result": "lose",
        "payout": 0
      }
    },
    {
      "id": "01fbff89-2dce-4646-bdce-36a3cd1b2368",
      "name": "ввввв",
      "nameKey": "ввввв",
      "balance": 1000,
      "createdAt": "2026-05-29T04:56:26.744Z",
      "lastDailyBonus": 0,
      "stats": {
        "gamesPlayed": 0,
        "wagered": 0,
        "won": 0,
        "biggestWin": 0
      },
      "history": [],
      "bj": null,
      "passwordSalt": "63cbfdaac355550ddcd8a0380159c4ba",
      "passwordHash": "d0008dbcfb673954ef4694e19d298cecd9ef7f5b3c26023120d46b738ca119288c2a2a099dd2cb62525581565feaf3c3b9bc0f273fab71290884eb33f9fbe0d5",
      "lastRescueBonus": 0
    }
  ],
  "config": {
    "economy": {
      "startingBalance": 1000,
      "minBet": 1,
      "maxBet": 100000,
      "dailyBonus": 500,
      "dailyCooldownHours": 20,
      "rescueBonus": 250,
      "rescueThreshold": 50
    },
    "coinflip": {
      "winChancePercent": 49,
      "winMultiplier": 1.97
    },
    "dice": {
      "houseEdgePercent": 2
    },
    "slots": {
      "weights": {
        "🍒": 28,
        "🍋": 24,
        "🔔": 18,
        "⭐": 14,
        "💎": 9,
        "7️⃣": 5
      },
      "triples": {
        "🍒": 3.18,
        "🍋": 4.77,
        "🔔": 9.54,
        "⭐": 19.87,
        "💎": 47.7,
        "7️⃣": 119.26
      },
      "twoCherry": 1.59,
      "oneCherry": 0.79
    },
    "roulette": {
      "enabled": true
    },
    "wheel": {
      "segments": [
        {
          "label": "0x",
          "multiplier": 0,
          "weight": 30,
          "color": "#38445f"
        },
        {
          "label": "1.5x",
          "multiplier": 0.48,
          "weight": 25,
          "color": "#2fe6a0"
        },
        {
          "label": "2x",
          "multiplier": 0.64,
          "weight": 18,
          "color": "#9d7bff"
        },
        {
          "label": "3x",
          "multiplier": 0.96,
          "weight": 13,
          "color": "#ffce54"
        },
        {
          "label": "5x",
          "multiplier": 1.6,
          "weight": 8,
          "color": "#ff8c42"
        },
        {
          "label": "10x",
          "multiplier": 3.21,
          "weight": 4,
          "color": "#ff5c7c"
        },
        {
          "label": "50x",
          "multiplier": 16.06,
          "weight": 2,
          "color": "#ff2d6f"
        }
      ]
    },
    "crash": {
      "houseEdgePercent": 3,
      "maxMultiplier": 1000
    },
    "blackjack": {
      "blackjackPayout": 1.5
    }
  }
}